wizardai/__init__.py
wizardai/build_report.py
wizardai/audits/__init__.py
wizardai/audits/preflight.py
wizardai/audits/sentiment.py
wizardai/audits/sentiment_perf.py
wizardai/audits/sentiment_safe.py
wizardai/pages/__init__.py
wizardai/pages/page_explain.py
wizardai/pages/page_main.py
wizardai/pages/page_perf.py
wizardai/pages/page_repairs.py
wizardai/pages/page_safe.py
wizardai/pages/run_audit.py
wizardai-0.0.1.dist-info/LICENSE
wizardai-0.0.1.dist-info/METADATA
wizardai-0.0.1.dist-info/WHEEL
wizardai-0.0.1.dist-info/top_level.txt
wizardai-0.0.1.dist-info/RECORD
